LICENCE.txt
README.md
setup.py
ga_hypertuner/__init__.py
ga_hypertuner/exceptions.py
ga_hypertuner/ga.py
ga_hypertuner/reporting.py
ga_hypertuner/tuner.py
ga_hypertuner/visualization.py
ga_hypertuner.egg-info/PKG-INFO
ga_hypertuner.egg-info/SOURCES.txt
ga_hypertuner.egg-info/dependency_links.txt
ga_hypertuner.egg-info/top_level.txt
ga_hypertuner/test/__init__.py
ga_hypertuner/test/first_example.py
ga_hypertuner/test/second_example.py