Metadata-Version: 2.1
Name: ga-hypertuner
Version: 1.0.0
Summary: A Hyperparameter Tuner for Machine Learning Algorithms Powered By Genetic Algorithm (Differential Evolution) 
Home-page: UNKNOWN
Author: Amirali Omidvar
Author-email: amirali.omidvar80@gmail.com
License: MIT
Platform: UNKNOWN
License-File: LICENCE.txt
